{"18":"know what is going","47":"Turquoise Trail","50":"Trail","2":"should always you know","69":"just green olives","80":"holy crap","16":"they don't have the ability say I'm a big business not sure which I have no disagreement with my dad said I think that the problem turns in later on when everything gets the store to me and start using them to me things that they don't lie mean and that's when you have the Distortion of history and that's when you have the Distortion of the ability to relate Eastern what something is it wanted to do you know","81":"holy crap","89":"don't","11":"you know","21":"whole world","46":"Turquoise Trail","82":"crap the jump-off show","85":"please don't fall","9":"you know","10":"you know","83":"the jump-off show","19":"know what is going on with in this country","17":"Eastern what something is it wanted to do you know what is going","8":"you know","49":"Trail","88":"I don't","73":"olives green","92":"it's","3":"know","72":"green olives green only","95":"you","79":"holy crap","20":"know what is going on with in this country you're a ghost the whole world","45":"Turquoise Trail","71":"just green olives green only","13":"Edition come from","14":"they","93":"it's the past","48":"Turquoise Trail","70":"just green olives green only","94":"okay thank you","15":"they don't have the ability to say I'm a big business not sure which I have no","12":"know the subject is progressivism verse classical River understand about Progressive philosophical faces Edition come from","1":"that someone should always you know"}