{"41":"a bullet stuck Bosque office inviting you to the closure I left.","40":"City defense please show to suck a bullet stuck Bosque office","16":"at the doctor. Just got was older Beyond if you","11":"love you","39":"Jet City defense please show to suck a bullet","7":"Gale subjective Monica liquor 15 Bundesliga judicial she","9":"if it isn't true to adequately boys I love you","25":"Judy's attic ninja push mower listen to Crimson technical service repair voltage is","10":"love you","26":"listen to Crimson technical service repair voltage is UTC lemon technique open","42":"to the closure I left. Bodega SLC","19":"are","17":"at the doctor. Just got was older Beyond if you get those will just be here but they said they are","8":"15 Bundesliga judicial she dog biscuit Atlanta Ice-T original to buy if it isn't true to adequately boys I","6":"Gale subjective","24":"Judy's attic ninja push mower listen","4":"Jim Gale subjective","37":"when you touch the last post","28":"technique open or recycle","5":"Gale subjective","20":"are","23":"Judy's attic ninja push mower","13":"York City","14":"okay","27":"service repair voltage is UTC lemon technique open or recycle","36":"when you touch","15":"at the doctor. Just got was older","12":"the owns a New York Acela New York City","18":"are"}