{"68":"going down basement","11":"baby baby bad","85":"could Betty","25":"you like Venus and Serena","55":"cheap baby chick do stuff that your chick wish","42":"Ed Sheehan","66":"Saskatchewan","58":"your chick wish she could touch eBay wish you could have done cheap heavy Betty","59":"wish you could have done cheap heavy Betty Danger's","8":"that chick this year","74":"Archie Bruce cooking for me","95":"Walmart","57":"do stuff that your chick wish she could touch eBay","20":"I can't even More Than Words.","14":"bad my chick Hood my chick do stuff that","78":"printing in SC sexy","33":"stuff that your chick wish she could hot","18":"badder than yours my chick do stuff that I can't even","69":"down","96":"and that's legit","26":"you like Venus and Serena in all white jeans body looking like milk no no time for","35":"hot chick do stuff that your chick wish","83":"stuff that your chick wish she could","17":"that your wish she could My Chick Bad badder than yours my chick do stuff that I can't even","49":"get drawn like cartoon","84":"wish could","4":"I'm still with your chick wish you could touch eBay","37":"your chick wish reviews turn on my GPS","13":"bad my chick","86":"Betty Danger's Mama cheese","67":"Saskatchewan then I have to run and it's going down","99":"I mean","1":"call Court small passes back to normal smothering","54":"cheap baby chick do","32":"stuff that your chick wish she","50":"get drawn like cartoon","77":"cheap printing in Florence SC","40":"Ed Sheehan","80":"sexy babes do","82":"stuff that your chick wish she could","91":"Barcelona roster","7":"antique Hood my chick do stuff that your chick this year","9":"that chick this year baby baby","75":"cheap printing in Florence","60":"Danger's","34":"stuff that your chick wish she could hot chick","87":"Danger's Mama cheese","3":"I'm still with your chick","79":"sexy babes","38":"turn on my GPS","71":"Archie Bruce cooking for","36":"chick do stuff that your chick wish reviews","48":"guns get drawn like cartoon","76":"cheap printing in Florence SC","12":"bad my","81":"babes do stuff that your chick wish she could","98":"up I mean","16":"bad my chick Hood my chick do stuff that your chick wish she could My Chick Bad badder than","10":"baby baby","19":"than yours my chick do stuff that I can't even More Than Words.","51":"get like cartoon","6":"could touch eBay antique Hood my chick do stuff that your chick","24":"you like Venus and Serena","73":"Archie Bruce cooking for me","92":"roster","53":"cheap baby","72":"Archie Bruce cooking for me","28":"body looking like milk no no time for change when she's gone","5":"still your chick wish you could touch eBay antique Hood my chick do","23":"you like Venus","27":"all white jeans body looking like milk no no time for change when she's gone","56":"chick do stuff that your chick wish she could touch","97":"and that's legit but I look it up I mean","41":"Ed Sheehan","15":"bad my chick Hood my chick do stuff that your chick"}