{"30":"animals","40":"call me on my Samsung phone","16":"another Shore","21":"Father and Son","39":"call me on my Samsung phone","26":"floor","25":"Father and Son construction floor","29":"animals","19":"mama told my papa I got you something about good","17":"Shore mama","22":"Father and Son","24":"Father and Son construction","28":"floor animals","38":"call me on my Samsung phone","20":"Father and","23":"Father and Son construction","14":"deceased another Shore","27":"floor","15":"another Shore","41":"Samsung","18":"mama told my"}