{"68":"to 1 2 3 4","148":"to get the road","89":"wait to get home flow the game on the road again","85":"to get on road why is making","136":"where is Best Buy","66":"1 to the 1 2 3 4","74":"on the","95":"if we go down","90":"flow the game on the road again","78":"the road","106":"the world","114":"just can't wait to get on the road","96":"if we go down where are the best friends","135":"where is","83":"just wait to get on the road","146":"just can't wait to get all the road","64":"1 to the 1 2 3 4","65":"1 to the 1 2 3 4","84":"wait to get on the road why","138":"where is Best Buy","86":"why is making music with my friend and I can't wait to get home","67":"to 1 2 3 4","99":"where are the best friends in the","117":"I is making music with my friend I can't wait to get","137":"where is Best Buy","94":"if we","115":"just can't wait to get on the road I love is making music with my friend","105":"the world","77":"the road","80":"the road just can't wait to get on the road","101":"are the best friends in the world","82":"just can't wait to get on the road","75":"the road","147":"just wait to get all the road","104":"in the world","87":"music with my friend and I can't wait to get home flow the game on the","103":"the best friends in the world","79":"the road","118":"is making music with my friend I can't wait to get home","76":"the road","100":"where are the best friends in the","81":"just can't wait to get on the road","98":"where are the best friends","62":"1 to","107":"the world","102":"are the best friends in the world","88":"wait to get home flow the game on the","119":"can't wait get home","116":"I love is making music with my friend I","63":"1 to the 1 2 3 4","97":"go where are the best friends"}