{"30":"Hut Rockwall","33":"play God Is My judge is looking to use an Apache","32":"resume uncle that you can play play God Is My judge is looking to use","16":"Swiss","26":"site of the Sea California","25":"Geisinger Appleton Latin America Visa what you want Vision by","35":"Casselton vet","34":"an Apache josi Casselton vet","29":"Pizza Hut Rockwall","19":"elephant obey Jimmy fuel filter Mania Cassidy Lost Boys y'all got to get some deals","17":"Swiss ball is it an","22":"look up what I say don't still feel sick where to go. So many tacos painter Essentials Ocala","24":"Geisinger Health Appleton","20":"y'all got to get some deals","23":"Essentials Ocala","13":"Shiloh McCool for a fact. is Shannon","14":"is Shannon Wilkinson you watch Survivor Moscow mule","31":"Hut Rockwall","27":"Sea","15":"Spotify High School Boston","12":"Shiloh","18":"Swiss ball is it an elephant obey Jimmy fuel filter"}