{"68":"you","100":"pictures of dogs the weather like","77":"if I get to work","69":"Fullerton transmission","89":"what time is","98":"if you do","101":"Jimbo Jennifer Lee","62":"I love you baby","109":"demo","96":"what's the weather message YouTube","85":"Trader Joe's","60":"I love you baby","66":"I love you baby","102":"Lee","58":"I","64":"I love you baby","59":"I love","65":"I love you baby","87":"Pizza Hut in Minden","84":"Trader Joe's","88":"what time is it","61":"I love you baby","110":"Manchester and Liverpool drawing on the right","111":"drawing on the right","63":"I love you baby","67":"I love you","112":"Icarus battle American Eagle near me Starved Rock","70":"transmission","76":"Northwest Bank","97":"YouTube","105":"comedy Atlanta"}