{"33":"it's okay up in Indian mythology","32":"show particular me.","11":"tell how long does persona show and guess what","21":"I want to watch mrs. Romano","39":"La Pasadita","7":"Menorah San Benito","9":"mobile","25":"mrs.","10":"tell how long does persona show","26":"wanton women","34":"call the dentist","35":"ISO Bella","17":"Karma","8":"Menorah San Benito mobile","22":"I want to watch mrs. Romano","6":"Atoka from Tennessee","24":"I want to mrs. Romano","37":"ISO Bella Chevy 05 Z71 let me tell you.","28":"wanton","5":"Atoka from","38":"Kevin Kilpatrick","20":"I want to watch mrs. Romano","23":"I want to watch mrs. Romano","13":"Samuel The Voice anymore","27":"wanton women","36":"ISO Bella Chevy 05","15":"download","12":"guess what Arrow Amanda Samuel","18":"Karma"}