{"32":"to shave","2":"take it to the stage","98":"feel it still meaning","16":"pictures of pretty sweet","96":"feel it still meaning","9":"what's the big deal","35":"you looked all the way up","34":"you looked all the way up","55":"what's","59":"I'm telling the truth","49":"sweet","6":"LaMotta grave distributed","4":"Jake LaMotta grave","37":"Google Now","5":"LaMotta grave","38":"Google Now","57":"what's happening","31":"to shave","67":"Storage King what happens when you walk","99":"meaning","48":"you take Johnny what channel is the sweet","56":"what's","97":"feel it still meaning","1":"let's take it to the stage"}