{"32":"check the clock who's not right","121":"then what","124":"shut up","40":"what are you doing","89":"Debby Ryan","91":"knocked out first","26":"I'll come in at 10:30 somebody my ShopRite 6 feet away","43":"stop","25":"ruby red","35":"what's a bad","75":"America","125":"up","135":"do not drink","144":"what's up","64":"open S Voice","65":"Wambach","155":"first one White","150":"you miss that walk not to call but still miss that work","44":"welcome back","73":"I did","88":"Debby Ryan","119":"if a little boy","145":"next one is","153":"you want me to answer that","149":"then you miss that walk not to call but still","139":"compound bow","38":"think about","45":"welcome back I need one you like that","31":"oh no no no hey","154":"first one","117":"I want to come in","27":"6 feet away ShopRite nice shot","126":"up","36":"a bad","30":"struggle"}