{"148":"now I wonder if I could","210":"that. I see you things when plasma","158":"do you think","160":"you think twin Pass Me","151":"wonder if I could fall into","181":"I think of you and I wonder if you ever think of me","131":"sneaking away","144":"the miss you now I","155":"sky do you think","207":"cancel that. I","142":"the miss you now","150":"now wonder if I could fall into","209":"that. I see you","199":"cuz I'm changing","74":"would you","201":"cuz I'm changing numbness","185":"Roblox","176":"I think of","78":"look at that","159":"do you think twin","205":"cancel","106":"would you rather","200":"cuz I'm changing","165":"twin Pass Me By","109":"you rather","96":"stream","182":"if ever think of me","166":"Pass Me By","133":"away","187":"Roblox","146":"you now I wonder if","130":"sneaking away","202":"cuz I'm changing numbness","145":"the you now I wonder if","127":"take them away downtown walking fast faces pass and I'm homebound","168":"Pass Me By","126":"take them away downtown walking fast","141":"the miss you","105":"would you rather","206":"cancel","77":"look at that","188":"Roblox","128":"fast faces pass and I'm homebound","132":"away","75":"would you","147":"now I wonder if","157":"sky do you think","183":"if ever think of me","178":"I think of you and I wonder","179":"I think of you and I wonder","198":"cuz I'm changing","153":"fall into the sky do","152":"could fall into the sky","154":"fall into the sky do you","76":"you just look at that","184":"ever think of me","167":"Pass Me By","143":"the miss you now","107":"would you rather","169":"Me","208":"cancel that. I see you","180":"I think of you and I wonder if you","161":"you think twin Pass Me By","162":"you twin Pass Me By","186":"Roblox","156":"sky do you think","177":"I think of you and","149":"now wonder if I could","163":"you twin Pass Me By","164":"twin Pass Me By","108":"would you rather","97":"stream"}