{"22":"where Swan Song today screen door sweet as real I Cry I live the swan song","24":"I'm so","13":"play Luke Bryan Ikea who said stream flowing play.","14":"and I know not to Terry but it's spelled words and my words remain unguarded and so I come to nothing","25":"I'm so Blue Jays me and the Ring song and no night","19":"so I read Myself and I learning letters woman cried annoying","15":"and I know cursive with me High School sweet ass real I cry and I will respond songs to me","21":"Coleridge to suspicion as I grow up whether it is my old bride who stays Young Swing Swing a crying where is Swan Song today","20":"cried annoying French flag how to draw Einstein Bagels Coleridge to"}