{"50":"chase the chance my little honey stop to dance enjoy the money","26":"horns and Hooves tail in muscle give me fun and take the muscle","25":"potty potty potty hotty the art funny Social Sports horns and Hooves tail in muscle give","35":"up and down all around in and out all about info Giant in front","34":"up and down all around","49":"chase the chance my little honey","24":"easy as can be easy peasy japanesey easy as knitting kitchen potty potty potty","37":"while Bush cobbler ding-a-dong give me problems take a song","38":"give me take a song","23":"it's easy as can be easy peasy japanesey","27":"give me fun and take the muscle","36":"in and all about info Giant in front now take what you want while Bush cobbler ding-a-dong"}