{"124":"is a fit for me","39":"well if you ain't got that cash imma need some collateral I got I got this necklace","46":"what is a basket","25":"what mean snowflake I am Percy Khalifa","55":"yo ho ve why would I","42":"my grandmother's handed it down to me it's pre-World War","29":"your is here","58":"would I it's right","66":"can he can cook I'm done you can keep him for like a week or so","59":"right","95":"flash about a month","57":"yo ve why would I say it's right","111":"first the world around","112":"world around","106":"anyway I'm off that top that skipping you like me to one person or first the whole world around","52":"yo ho ve","121":"how much is Eugene","109":"one or first the whole world around","96":"flash about a month get out","26":"Percy Khalifa hey yo Khalifa when your custy's is","35":"I need","125":"is a fit for me","64":"person funny he can he can cook I'm","65":"person funny he can he can cook I'm done you can","44":"handed it down to me it's pre-World War","37":"need something to hold me for like a week you got that cash well if","110":"or first the whole world around","127":"a for me","45":"handed it to me it's pre-World War what is a basket","67":"like a week or so","99":"out anyway","93":"flash","126":"a fit for me","94":"flash about a","105":"anyway I'm off that top that skipping you like me to one","47":"what is a basket","54":"yo ho ve","40":"imma need some I got I got this necklace it was my grandmother's handed it down to me it's pre-World","101":"anyway I'm off that top that","43":"my handed it down to me it's pre-World War","128":"for me","34":"I","104":"anyway I'm off that top that skipping you like","103":"anyway I'm off that top that skipping you","38":"got that cash well if you ain't got that cash imma need some","120":"how","36":"I need something to hold me down for like a week you got that cash","113":"world around","100":"out anyway I'm off","98":"out","122":"how much Eugene is a fit for me","62":"yo Dre this is my roommate Tim","107":"you me to one person or first the whole world around","21":"are you","102":"anyway I'm off that top that skipping","129":"for me","22":"are you here for","24":"what you mean snowflake I am Percy","53":"yo ho ve","123":"is a fit for me","28":"Khalifa your custy's is here","23":"you here for what you mean","63":"yo Dre this is my roommate Tim she he's a really nice person he's funny he can he can cook","27":"yo Khalifa when your custy's is here","56":"yo ve why would I say","97":"get out","108":"me to one person or first the whole world around","41":"was my grandmother's handed it down to me it's pre-World War"}