{"68":"what does a trivia.","210":"Alaska Alaska","288":"official spend it on Frankie Lymon","267":"look up solution Attack on Titan","306":"Billie","370":"It Up","360":"Shakira mean","215":"yuck","382":"Realtors no we better move. Thrasher Opera","66":"what does a trivia.","181":"I'll take some in Korean","193":"La Concorde","365":"that one Reynosa","239":"Alexandre De La Mirada","209":"Alaska Alaska","296":"Mariano IMDb","384":"Aventura","236":"Anthony Joshua","283":"pollution antecedent","285":"antecedent GoNoodle fastest","70":"what does a trivia.","205":"Arab Republic electricity versus kilometers I'll call you later Mario","106":"story","372":"how do you wanna Spinoza","212":"yuck","308":"malic acid","69":"what does a trivia.","165":"scans","265":"Channel","269":"on psychology","278":"Cinnabon Las Vegas","336":"Airport cinema","64":"what does","65":"what does a","298":"Apollo the pup that pressed. Casimir","286":"fastest route to Tessa compartir apocrypha","292":"Super Wings on Buena Vista films are popular still in perspective","192":"call did I interview yesterday La Concorde","230":"a mighty important matchup","235":"Anthony Joshua","263":"una pelicula de Rosa Clara I hear America Mira unicorn Channel","357":"Shakira","346":"stop.","67":"what does a trivia.","105":"best contact lenses story","284":"pollution antecedent GoNoodle","206":"kilometers I'll call you later Mario","229":"a mighty important","190":"cuz I need to do a couple call","211":"yuck","214":"yuck","307":"Billie Jean ecologic","373":"how do you wanna Spinoza Teresa","359":"Shakira mean","303":"cincuenta mean Episcopal","203":"the business","337":"Airport cinema","381":"when I leave Arsenal Allen Tate Realtors","264":"I hear America Mira unicorn Channel","231":"mighty important matchup","273":"Alphonse alibi","178":"open Apollo.","363":"missing that one Reynosa","345":"stop.","313":"Jessica Laguna Splash La Mirada","383":"Thrasher Opera Aventura","330":"Honeywell quietset fan the weather when I want Association","71":"what does a trivia.","295":"Ativan","293":"call Mama sister penguin","213":"yuck","204":"the business opportunity Arab Republic","291":"Super Wings on Buena Vista films are popular","297":"Mariano IMDb Apollo the pup that","287":"apocrypha the official spend it on Frankie Lymon","304":"cincuenta Episcopal important alkali","364":"missing that one Reynosa","374":"Teresa","208":"Hollywood","180":"I'll take some in Korean","294":"call sister penguin Ativan","161":"the special device company at Damariscotta scans","162":"the special device company at Damariscotta scans","268":"up solution Attack on Titan","281":"hookah bar","280":"hookah bar","240":"Alexandre De La Mirada","73":"does a","119":"mint.com","260":"3140 Vista","191":"cuz I need do a couple call did I interview yesterday","177":"open Apollo.","262":"Daniel Castillo una pelicula de Rosa Clara","274":"Alphonse alibi","261":"Daniel Castillo","72":"what does a","277":"Cinnabon Las","312":"Jessica Laguna","380":"nomadic when I leave Arsenal","358":"Shakira mean","63":"what","163":"the special company at Damariscotta scans","305":"important alkali when a table set solid","331":"when I want Association","369":"Pump It Up","164":"scans","362":"missing that one Reynosa"}