{"68":"monster tattoo","39":"Wrecking Ball","46":"Ball live","134":"stop.","136":"stop.","382":"deuces","42":"Ball live","131":"stop.","20":"Walmart","70":"monster tattoo","18":"Walmart","388":"deuces","69":"monster tattoo","451":"Daniel","219":"spectacular","223":"spectacular","182":"original","133":"stop.","135":"stop.","452":"Daniel","130":"stop.","17":"Walmart","387":"deuces","44":"Ball live","220":"spectacular","436":"deuces","460":"beautiful","127":"stop.","45":"Ball live","450":"damn Daniel","67":"monster tattoo","93":"done bad things","137":"stop.","94":"done bad things","47":"Ball live","40":"Wrecking Ball live","43":"Ball live","128":"stop.","132":"stop.","470":"do cigars","381":"deuces","183":"original","221":"spectacular","217":"spectacular","383":"deuces","71":"monster tattoo","469":"hell do cigars","48":"Ball","184":"original","224":"spectacular","21":"Walmart","19":"Walmart","389":"deuces","129":"stop.","73":"monster","92":"done bad things","222":"spectacular","72":"monster tattoo","218":"spectacular","41":"Ball live"}