{"18":"squats","30":"to spoil American chicken house okay","33":"chicken house","32":"chicken house okay","47":"mouth now Donuts","2":"a ladies and gentlemen now we're going to play the game the game call Donna sis you have to do you have to do what Donna says you have to do I like that again very much","50":"Jasmine Place music","52":"Jasmine Place music","16":"driving otherwise let's jump","11":"on one leg","21":"British man squatting squatting","26":"Bach finger one finger daddy finger one figured you're not doing","9":"on one leg","25":"Bach finger one finger daddy finger one figured","10":"on one leg","34":"house concentration","29":"don't like way to spoil my American chicken house okay","35":"concentration Tyson Tyson Tyson","19":"squats squats and squats and it's quietin okay","17":"let's jump squats","49":"Donuts dance lesson Jasmine Place music","22":"man squatting squatting squatting","51":"Jasmine Place music","24":"Bach finger one finger daddy","4":"like that again much okay when Donna says okay no exception if you make another exception I kicking you out of the studio okay not good sense","37":"Tyson Tyson Tyson Tyson Tyson wait at night now.","3":"have to do Donna says you have to do I like that again very much okay when Donna","28":"doing don't like the way to spoil my American chicken house okay","38":"at night now.","20":"and squats and it's quietin okay British man","23":"squatting squatting","13":"driving otherwise","14":"driving otherwise","31":"American chicken house okay","27":"Bach finger one finger daddy finger one figured you're not doing I don't like the way to spoil my American chicken","36":"concentration Tyson Tyson Tyson Tyson Tyson wait at night now.","48":"now Donuts dance lesson","15":"driving otherwise let's jump","12":"on one leg driving otherwise","1":"a ladies and gentlemen"}